<?xml version="1.0" encoding="UTF-8"?>
<root>
    <defaultteam phone="13339505100" id="0" leader="1">
        <!--team id是0的为默认组 -->
        <man>
            <name>白亮</name>
            <phone>13339505100</phone>
            <id>1</id>
        </man>
        <man>
            <name>周贺挺</name>
            <phone>13339505123</phone>
            <id>2</id>
        </man>
    </defaultteam>
    <team phone="13339505100" id="1" leader="1">
        <man>
            <name>白亮</name>
            <phone>13339505100</phone>
            <id>1</id>
        </man>
        <man>
            <name>周贺挺</name>
            <phone>13339505123</phone>
            <id>2</id>
        </man>
    </team>
    <team phone="13339505101" id="2" leader="1">
        <man>
            <name>白亮</name>
            <phone>13339505100</phone>
            <id>1</id>
        </man>
    </team>
    <team phone="13339505102" id="3" leader="1">
        <man>
            <name>白亮</name>
            <phone>13339505100</phone>
            <id>1</id>
        </man>
    </team>
    <team phone="13339505103" id="4" leader="1">
        <man>
            <name>白亮</name>
            <phone>13339505100</phone>
            <id>1</id>
        </man>
    </team>
    <team phone="13339505104" id="5" leader="1">
        <man>
            <name>白亮</name>
            <phone>13339505100</phone>
            <id>1</id>
        </man>
    </team>
    <team phone="13339505105" id="6" leader="1">
        <man>
            <name>白亮</name>
            <phone>13339505100</phone>
            <id>1</id>
        </man>
    </team>
    <team phone="13339505106" id="7" leader="1">
        <man>
            <name>白亮</name>
            <phone>13339505100</phone>
            <id>1</id>
        </man>
    </team>
</root>
